rassine/__init__.py
rassine/imports/__init__.py
rassine/imports/data.py
rassine/imports/preprocess_import.py
rassine/imports/preprocess_table.py
rassine/imports/reinterpolate.py
rassine/lib/__init__.py
rassine/lib/analysis.py
rassine/lib/data.py
rassine/lib/io.py
rassine/lib/math.py
rassine/lib/util.py
rassine/matching/__init__.py
rassine/matching/data.py
rassine/matching/matching_anchors_filter.py
rassine/matching/matching_anchors_scan.py
rassine/matching/matching_diff.py
rassine/rassine/__init__.py
rassine/rassine/data.py
rassine/rassine/functions.py
rassine/rassine/parsing.py
rassine/rassine/process.py
rassine/rassine/rassine.py
rassine/stacking/__init__.py
rassine/stacking/data.py
rassine/stacking/stacking_create_groups.py
rassine/stacking/stacking_master_spectrum.py
rassine/stacking/stacking_stack.py
rassine/tools/__init__.py
rassine/tools/compare_normalized_output.py
rassine/tools/enumerate_table_column_unique_values.py
rassine/tools/enumerate_table_rows.py
rassine/tools/pickle_compare.py
rassine/tools/reorder_csv.py
rassine/tools/sort_csv.py
rassine-0.4.0.dist-info/entry_points.txt
rassine-0.4.0.dist-info/WHEEL
rassine-0.4.0.dist-info/METADATA
rassine-0.4.0.dist-info/RECORD
